halo/__init__.py
halo/_utils.py
halo/cursor.py
halo/halo.py
halo/halo_notebook.py
halo-0.0.30.dist-info/LICENSE
halo-0.0.30.dist-info/METADATA
halo-0.0.30.dist-info/WHEEL
halo-0.0.30.dist-info/top_level.txt
halo-0.0.30.dist-info/RECORD
