Metadata-Version: 2.1
Name: halo
Version: 0.0.30
Summary: Beautiful terminal spinners in Python
Home-page: https://github.com/manrajgrover/halo
Author: Manraj Singh
Author-email: manrajsinghgrover@gmail.com
License: MIT
Keywords: console,loading,indicator,progress,cli,spinner,spinners,terminal,term,busy,wait,idle
Platform: UNKNOWN
Provides-Extra: ipython
